leveldiagram/__init__.py
leveldiagram/artists.py
leveldiagram/ld.py
leveldiagram/utils.py
leveldiagram-0.3.2.dist-info/LICENSE.md
leveldiagram-0.3.2.dist-info/METADATA
leveldiagram-0.3.2.dist-info/WHEEL
leveldiagram-0.3.2.dist-info/top_level.txt
leveldiagram-0.3.2.dist-info/RECORD
