Metadata-Version: 2.1
Name: leveldiagram
Version: 0.3.2
Summary: Energy level diagram plotting from graphs
Author: David Meyer
License: BSD-3-Clause
Keywords: physics,diagram,graph
Classifier: Programming Language :: Python :: 3 :: Only
Classifier: Programming Language :: Python :: 3.8
Classifier: Programming Language :: Python :: 3.9
Classifier: Programming Language :: Python :: 3.10
Classifier: Programming Language :: Python :: 3.11
Requires-Python: >=3.8
License-File: LICENSE.md
Requires-Dist: numpy
Requires-Dist: matplotlib
Requires-Dist: networkx
Provides-Extra: docs
Requires-Dist: Sphinx==7.2.6; extra == "docs"
Requires-Dist: sphinx-rtd-theme==2.0.0; extra == "docs"
Requires-Dist: nbconvert; extra == "docs"
Requires-Dist: pandoc; extra == "docs"
Provides-Extra: linter
Requires-Dist: ruff; extra == "linter"
Provides-Extra: mypy
Requires-Dist: mypy; extra == "mypy"
Requires-Dist: numpy>=1.21; extra == "mypy"
Requires-Dist: lxml; extra == "mypy"
